monitor_api/__init__.py
monitor_api/enums.py
monitor_api/monitor.py
monitor_api/core/__init__.py
monitor_api/core/collections.py
monitor_api/core/entities.py
monitor_api/dialects/__init__.py
monitor_api/dialects/dialect.py
monitor_api/dialects/local.py
monitor_api/dialects/remote.py
monitor_server/__init__.py
monitor_server/app.py
monitor_server/config.py
monitor_server/uwsgi.py
monitor_server/api/__init__.py
monitor_server/api/components.py
monitor_server/api/entry_points.py
monitor_server/api/execution_context.py
monitor_server/api/metrics.py
monitor_server/api/model.py
monitor_server/api/pager_utils.py
monitor_server/api/pipelines.py
monitor_server/api/resources.py
monitor_server/api/sessions.py
monitor_server/data/__init__.py
monitor_server/data/model.py
monitor_server/templates/index.html
monitor_server_api-1.1.0.data/scripts/launch-monitor-server.sh
monitor_server_api-1.1.0.dist-info/AUTHORS
monitor_server_api-1.1.0.dist-info/LICENSE
monitor_server_api-1.1.0.dist-info/METADATA
monitor_server_api-1.1.0.dist-info/WHEEL
monitor_server_api-1.1.0.dist-info/entry_points.txt
monitor_server_api-1.1.0.dist-info/top_level.txt
monitor_server_api-1.1.0.dist-info/RECORD
