Metadata-Version: 2.1
Name: monitor-server-api
Version: 1.1.0
Summary: A REST API that can be used a central point for collecting metrics from pytest-monitor.
Home-page: https://monitor-server-api.readthedocs.io/
Author: Jean-Sébastien Dieu
Author-email: dieu.jsebastien@yahoo.com
Maintainer: Jean-Sébastien Dieu
Maintainer-email: dieu.jsebastien@yahoo.com
License: MIT
Project-URL: Source, https://github.com/CFMTech/monitor-server-api
Project-URL: Tracker, https://github.com/CFMTech/monitor-server-api/issues
Classifier: Development Status :: 5 - Production/Stable
Classifier: Framework :: Pytest
Classifier: Intended Audience :: Developers
Classifier: Programming Language :: Python
Classifier: Programming Language :: Python :: 3
Classifier: Programming Language :: Python :: 3.7
Classifier: Programming Language :: Python :: 3.8
Classifier: Programming Language :: Python :: 3.9
Classifier: Programming Language :: Python :: Implementation :: CPython
Classifier: Programming Language :: Python :: Implementation :: PyPy
Classifier: Operating System :: OS Independent
Classifier: License :: OSI Approved :: MIT License
Requires-Python: >=3.6
License-File: LICENSE
License-File: AUTHORS
Requires-Dist: flask-restx
Requires-Dist: flask-sqlalchemy
Requires-Dist: requests
Requires-Dist: werkzeug (<2.0.0)
Requires-Dist: uwsgi
Requires-Dist: flask (<2.0.0)
Requires-Dist: pandas
Requires-Dist: wheel
Requires-Dist: pyyaml
Requires-Dist: sqlalchemy
